src/pifo_test/rtl/pifo_reg.v
`timescale 1ns/1ps

module pifo_reg
#(
    parameter L2_REG_WIDTH = 4,
    parameter RANK_WIDTH = 16,
    parameter META_WIDTH = 12
)
(
    input                       rst,
    input                       clk,

    // Insertion interface
    output reg                  full,
    input                       insert,
    input [RANK_WIDTH-1:0]      rank_in,
    input [META_WIDTH-1:0]      meta_in,

    // Removal interface
    output reg                  valid_out,
    input                       remove,
    output [RANK_WIDTH-1:0]     rank_out,
    output [META_WIDTH-1:0]     meta_out,

    // Max entry (evicted upon inserting into full reg)
    output reg                  max_valid_out,
    output [RANK_WIDTH-1:0]     max_rank_out,
    output [META_WIDTH-1:0]     max_meta_out,

    // Stats
    output reg [L2_REG_WIDTH:0] num_entries,
    output reg                  empty
);

    localparam REG_WIDTH = 2**L2_REG_WIDTH;
    localparam COMP_LVLS = L2_REG_WIDTH+1;

    reg [RANK_WIDTH-1:0] rank[0:REG_WIDTH-1];
    reg [META_WIDTH-1:0] meta[0:REG_WIDTH-1];
    reg valid[0:REG_WIDTH-1];
    reg [RANK_WIDTH-1:0] min_rank[0:COMP_LVLS-1][0:REG_WIDTH-1];
    reg [META_WIDTH-1:0] min_meta[0:COMP_LVLS-1][0:REG_WIDTH-1];
    reg [L2_REG_WIDTH-1:0] min_idx[0:COMP_LVLS-1][0:REG_WIDTH-1];
    reg [RANK_WIDTH-1:0] max_rank[0:COMP_LVLS-1][0:REG_WIDTH-1];
    reg [META_WIDTH-1:0] max_meta[0:COMP_LVLS-1][0:REG_WIDTH-1];
    reg [L2_REG_WIDTH-1:0] max_idx[0:COMP_LVLS-1][0:REG_WIDTH-1];
    reg mvalid[0:COMP_LVLS-1][0:REG_WIDTH-1];
    wire [L2_REG_WIDTH-1:0] idx;
    reg insert_ltch;
    reg calc_min_max;
    integer i, j;
    reg [RANK_WIDTH-1:0] rank_in_ltch;
    reg [META_WIDTH-1:0] meta_in_ltch;
    
   always @(*)
    begin
        for (j = 0; j < REG_WIDTH; j=j+1)
        begin
            min_rank[0][j] <= rank[j];
            min_meta[0][j] <= meta[j];
            min_idx[0][j]  <= j;
            max_rank[0][j] <= rank[j];
            max_meta[0][j] <= meta[j];
            max_idx[0][j]  <= j;
            mvalid[0][j]   <= valid[j];
        end

        for (i = 0; i < COMP_LVLS; i=i+1)
            for (j = 0; j < REG_WIDTH/2**i; j=j+2) 
            begin
                if (((min_rank[i][j] <= min_rank[i][j+1]) && (mvalid[i][j] == 1'b1) && (mvalid[i][j+1] == 1'b1)) ||
                    ((mvalid[i][j] == 1'b1) && (mvalid[i][j+1] !== 1'b1)))
                begin
                    min_rank[i+1][j/2] <= min_rank[i][j];
                    min_meta[i+1][j/2] <= min_meta[i][j];
                    min_idx[i+1][j/2]  <= min_idx[i][j];
                end
                else begin
                    min_rank[i+1][j/2] <= min_rank[i][j+1];
                    min_meta[i+1][j/2] <= min_meta[i][j+1];
                    min_idx[i+1][j/2]  <= min_idx[i][j+1];                      
                end
                
                if (((max_rank[i][j] > max_rank[i][j+1]) && (mvalid[i][j] == 1'b1) && (mvalid[i][j+1] == 1'b1)) ||
                    ((mvalid[i][j] == 1'b1) && (mvalid[i][j+1] !== 1'b1)))
                begin
                    max_rank[i+1][j/2] <= max_rank[i][j];
                    max_meta[i+1][j/2] <= max_meta[i][j];
                    max_idx[i+1][j/2]  <= max_idx[i][j];
                end
                else begin
                    max_rank[i+1][j/2] <= max_rank[i][j+1];
                    max_meta[i+1][j/2] <= max_meta[i][j+1];
                    max_idx[i+1][j/2]  <= max_idx[i][j+1];                      
                end
                
                if ((mvalid[i][j] == 1'b1) || (mvalid[i][j+1] == 1'b1))
                    mvalid[i+1][j/2] <= 1'b1;
                else
                    mvalid[i+1][j/2] <= 1'b0;
            end
    end

    // Output min and max
    assign rank_out = min_rank[COMP_LVLS-1][0];
    assign meta_out = min_meta[COMP_LVLS-1][0];
    assign idx = min_idx[COMP_LVLS-1][0];
    assign max_rank_out = max_rank[COMP_LVLS-1][0];
    assign max_meta_out = max_meta[COMP_LVLS-1][0];
    
    // Min/max valid generation
    always @(posedge clk)
    begin
        if (rst)
        begin
            valid_out <= 1'b0;
            max_valid_out <= 1'b0;
        end
        else
        begin
            if (insert == 1'b1 || remove == 1'b1)
            begin
                valid_out <= 1'b0;
                max_valid_out <= 1'b0;
            end

            if (calc_min_max == 1'b1)
                if (num_entries > 0)
                begin
                    valid_out <= 1'b1;
                    max_valid_out <= 1'b1;
                end
        end
    end
        
    // Insert/Remove
    always @(posedge clk)
    begin
        if (rst)
        begin
            num_entries <= 0;
            calc_min_max <= 0;
            insert_ltch <= 0;
            empty <= 1'b0;
            full <= 1'b0;
        end
        else 
        begin
            calc_min_max <= 0;
            
            if (remove == 1'b1 && num_entries > 0)
            begin
                // Close gap 
                for (i = 0; i < REG_WIDTH; i=i+1)
                    if (i > idx)
                    begin
                        rank[i-1] <= rank[i];
                        meta[i-1] <= meta[i];
                        valid[i-1] <= valid[i];
                    end
                valid[num_entries-1] <= 0;
                if (num_entries == 1)
                    empty <= 1'b1;
                full <= (insert == 0) ? 1'b0 : full;
                num_entries <= num_entries - 1;
                calc_min_max <= 1;
                insert_ltch <= insert;
                rank_in_ltch <= rank_in;
                meta_in_ltch <= meta_in;
            end
            else if (insert == 1'b1 || insert_ltch == 1'b1)
            begin
                // Insert new value at end of register
                if (num_entries < REG_WIDTH)
                begin
                    rank[num_entries] <= (insert) ? rank_in : rank_in_ltch;
                    meta[num_entries] <= (insert) ? meta_in : meta_in_ltch;
                    valid[num_entries] <= 1;
                    if (num_entries == REG_WIDTH-1)
                        full <= 1'b1;
                    else
                        full <= 1'b0;
                    num_entries <= num_entries + 1;
                end
                else
                begin
                    // If new value is smaller than max
                    if (insert) begin
                        if (rank_in < max_rank[COMP_LVLS-1][0]) begin
                            // Replace largest value
                            rank[max_idx[COMP_LVLS-1][0]] <= rank_in;
                            meta[max_idx[COMP_LVLS-1][0]] <= meta_in;
                        end
                    end
                    else begin
                        if (rank_in_ltch < max_rank[COMP_LVLS-1][0]) begin
                            // Replace largest value
                            rank[max_idx[COMP_LVLS-1][0]] <= rank_in_ltch;
                            meta[max_idx[COMP_LVLS-1][0]] <= meta_in_ltch;
                        end
                    end
                    full <= 1'b1;
                end
                empty <= 1'b0;
                calc_min_max <= 1;
                insert_ltch <= 0;
            end
        end
    end
    
endmodule

src/pifo_test/wrappers/pifo_reg_wrapper.v
module pifo_reg_wrapper (
    output reg clk,
    input rst,

    input insert,
    input [15:0] rank_in,
    input [11:0] meta_in,

    input remove,

    output valid_out,
    output [15:0] rank_out,
    output [11:0] meta_out,
    output empty,
    output full,

    output max_valid_out,
    output [15:0] max_rank_out,
    output [11:0] max_meta_out,
    output [4:0] num_entries
);

pifo_reg dut (
    .clk(clk),
    .rst(rst),
    .insert(insert),
    .rank_in(rank_in),
    .meta_in(meta_in),
    .remove(remove),
    .valid_out(valid_out),
    .rank_out(rank_out),
    .meta_out(meta_out),
    .max_valid_out(max_valid_out),   
    .max_rank_out(max_rank_out),
    .max_meta_out(max_meta_out),
    .num_entries(num_entries),
    .empty(empty),
    .full(full)
);

initial begin
    $dumpfile("pifo_sim.vcd");
    $dumpvars(0, pifo_reg_wrapper);  
    clk = 0;
    forever #5 clk = ~clk;
end

endmodule

src/pifo_test/tests/pifo_sim.vcd
$date
	Fri Oct  3 18:42:19 2025
$end
$version
	Icarus Verilog
$end
$timescale
	1ps
$end
$scope module pifo_reg_wrapper $end
$var wire 1 ! insert $end
$var wire 12 " meta_in [11:0] $end
$var wire 16 # rank_in [15:0] $end
$var wire 1 $ remove $end
$var wire 1 % rst $end
$var wire 1 & valid_out $end
$var wire 16 ' rank_out [15:0] $end
$var wire 5 ( num_entries [4:0] $end
$var wire 12 ) meta_out [11:0] $end
$var wire 1 * max_valid_out $end
$var wire 16 + max_rank_out [15:0] $end
$var wire 12 , max_meta_out [11:0] $end
$var wire 1 - full $end
$var wire 1 . empty $end
$var reg 1 / clk $end
$scope module dut $end
$var wire 1 / clk $end
$var wire 4 0 idx [3:0] $end
$var wire 1 ! insert $end
$var wire 12 1 max_meta_out [11:0] $end
$var wire 16 2 max_rank_out [15:0] $end
$var wire 12 3 meta_in [11:0] $end
$var wire 12 4 meta_out [11:0] $end
$var wire 16 5 rank_in [15:0] $end
$var wire 16 6 rank_out [15:0] $end
$var wire 1 $ remove $end
$var wire 1 % rst $end
$var parameter 33 7 COMP_LVLS $end
$var parameter 32 8 L2_REG_WIDTH $end
$var parameter 32 9 META_WIDTH $end
$var parameter 32 : RANK_WIDTH $end
$var parameter 32 ; REG_WIDTH $end
$var reg 1 < calc_min_max $end
$var reg 1 . empty $end
$var reg 1 - full $end
$var reg 1 = insert_ltch $end
$var reg 1 * max_valid_out $end
$var reg 12 > meta_in_ltch [11:0] $end
$var reg 5 ? num_entries [4:0] $end
$var reg 16 @ rank_in_ltch [15:0] $end
$var reg 1 & valid_out $end
$var integer 32 A i [31:0] $end
$var integer 32 B j [31:0] $end
$upscope $end
$upscope $end
$enddefinitions $end
$comment Show the parameter values. $end
$dumpall
b10000 ;
b10000 :
b1100 9
b100 8
b101 7
$end
#0
$dumpvars
bx B
bx A
bx @
bx ?
bx >
x=
x<
bx 6
b0 5
bx 4
b0 3
bx 2
bx 1
bx 0
0/
x.
x-
bx ,
bx +
x*
bx )
bx (
bx '
x&
1%
0$
b0 #
b0 "
0!
$end
#5000
0*
0&
0-
0.
0=
0<
b0 (
b0 ?
1/
#10000
0%
0/
#15000
1/
#20000
0/
#25000
1/
#30000
1!
b100010100011 "
b100010100011 3
b101101100000 #
b101101100000 5
0/
#35000
b100010100011 ,
b100010100011 1
b101101100000 +
b101101100000 2
b0 0
b100010100011 )
b100010100011 4
b101101100000 '
b101101100000 6
b101 A
b10 B
1<
b1 (
b1 ?
1/
#40000
0!
0/
#45000
1*
1&
0<
1/
#50000
0/
#55000
1/
#60000
1!
b111010000101 "
b111010000101 3
b1110110100010100 #
b1110110100010100 5
0/
#65000
b111010000101 ,
b111010000101 1
b1110110100010100 +
b1110110100010100 2
b101 A
b10 B
0*
0&
1<
b10 (
b10 ?
1/
#70000
0!
0/
#75000
0<
1*
1&
1/
#80000
0/
#85000
1/
#90000
1!
b101011011 "
b101011011 3
b1110101000110000 #
b1110101000110000 5
0/
#95000
b101 A
b10 B
1<
b11 (
b11 ?
0*
0&
1/
#100000
0!
0/
#105000
1*
1&
0<
1/
#110000
0/
#115000
1/
#120000
1$
0/
#125000
b1 0
b101011011 )
b101011011 4
b1110101000110000 '
b1110101000110000 6
b10 B
0*
0&
b101011011 >
b1110101000110000 @
1<
b10 (
b10 ?
b101 A
1/
#130000
0$
0/
#135000
0<
1*
1&
1/
#140000
0/
#145000
1/
#150000
1!
b1011101100 "
b1011101100 3
b101010110110011 #
b101010110110011 5
0/
#155000
b10 0
b1011101100 )
b1011101100 4
b101010110110011 '
b101010110110011 6
b101 A
b10 B
1<
b11 (
b11 ?
0*
0&
1/
#160000
0!
0/
#165000
1*
1&
0<
1/
#170000
0/
#175000
1/
#180000
1!
b110001100 "
b110001100 3
b1001110110010100 #
b1001110110010100 5
0/
#185000
b101 A
b10 B
0*
0&
1<
b100 (
b100 ?
1/
#190000
0!
0/
#195000
0<
1*
1&
1/
#200000
0/
#205000
1/
#210000
1$
0/
#215000
b110001100 )
b110001100 4
b1001110110010100 '
b1001110110010100 6
b10 B
b110001100 >
b1001110110010100 @
1<
b11 (
b11 ?
0*
0&
b101 A
1/
#220000
0$
0/
#225000
1*
1&
0<
1/
#230000
0/
#235000
1/
#240000
1!
b1111010011 "
b1111010011 3
b11000011000010 #
b11000011000010 5
0/
#245000
b11 0
b1111010011 )
b1111010011 4
b11000011000010 '
b11000011000010 6
b101 A
b10 B
0*
0&
1<
b100 (
b100 ?
1/
#250000
0!
0/
#255000
0<
1*
1&
1/
#260000
0/
#265000
1/
#270000
1$
0/
#275000
b10 0
b110001100 )
b110001100 4
b1001110110010100 '
b1001110110010100 6
b10 B
b1111010011 >
b11000011000010 @
1<
b11 (
b11 ?
0*
0&
b101 A
1/
#280000
0$
0/
#285000
1*
1&
0<
1/
#290000
0/
#295000
1/
#300000
1!
b10101011101 "
b10101011101 3
b1101111111000110 #
b1101111111000110 5
0/
#305000
b101 A
b10 B
0*
0&
1<
b100 (
b100 ?
1/
#310000
0!
0/
#315000
0<
1*
1&
1/
#320000
0/
#325000
1/
#330000
1$
0/
#335000
b10101011101 )
b10101011101 4
b1101111111000110 '
b1101111111000110 6
b10 B
b10101011101 >
b1101111111000110 @
1<
b11 (
b11 ?
0*
0&
b101 A
1/
#340000
0$
0/
#345000
1*
1&
0<
1/
#350000
0/
#355000
1/
#360000
1!
b100011010001 "
b100011010001 3
b1110101011111100 #
b1110101011111100 5
0/
#365000
b101 A
b10 B
0*
0&
1<
b100 (
b100 ?
1/
#370000
0!
0/
#375000
0<
1*
1&
1/
#380000
0/
#385000
1/
#390000
1$
0/
#395000
b1 0
b101011011 )
b101011011 4
b1110101000110000 '
b1110101000110000 6
b10 B
b100011010001 >
b1110101011111100 @
1<
b11 (
b11 ?
0*
0&
b101 A
1/
#400000
0$
0/
#405000
1*
1&
0<
1/
#410000
0/
#415000
1/
#420000
1$
0/
#425000
b100011010001 )
b100011010001 4
b1110101011111100 '
b1110101011111100 6
b10 B
0*
0&
1<
b10 (
b10 ?
b101 A
1/
#430000
0$
0/
#435000
0<
1*
1&
1/
#440000
0/
#445000
1/
#450000
1!
b110011101 "
b110011101 3
b110000100011110 #
b110000100011110 5
0/
#455000
b10 0
b110011101 )
b110011101 4
b110000100011110 '
b110000100011110 6
b101 A
b10 B
1<
b11 (
b11 ?
0*
0&
1/
#460000
0!
0/
#465000
1*
1&
0<
1/
#470000
0/
#475000
1/
#480000
1!
b11101110011 "
b11101110011 3
b10001110111100 #
b10001110111100 5
0/
#485000
b11 0
b11101110011 )
b11101110011 4
b10001110111100 '
b10001110111100 6
b101 A
b10 B
0*
0&
1<
b100 (
b100 ?
1/
#490000
0!
0/
#495000
0<
1*
1&
1/
#500000
0/
#505000
1/
#510000
1!
b101101010011 "
b101101010011 3
b1110000100 #
b1110000100 5
0/
#515000
b100 0
b101101010011 )
b101101010011 4
b1110000100 '
b1110000100 6
b101 A
b10 B
1<
b101 (
b101 ?
0*
0&
1/
#520000
0!
0/
#525000
1*
1&
0<
1/
#530000
0/
#535000
1/
#540000
1!
b110101001010 "
b110101001010 3
b11111101000000 #
b11111101000000 5
0/
#545000
b101 A
b10 B
0*
0&
1<
b110 (
b110 ?
1/
#550000
0!
0/
#555000
0<
1*
1&
1/
#560000
0/
#565000
1/
#570000
1!
b1010111000 "
b1010111000 3
b1110001010011 #
b1110001010011 5
0/
#575000
b101 A
b10 B
1<
b111 (
b111 ?
0*
0&
1/
#580000
0!
0/
#585000
1*
1&
0<
1/
#590000
0/
#595000
1/
#600000
1$
0/
#605000
b101 0
b1010111000 )
b1010111000 4
b1110001010011 '
b1110001010011 6
b10 B
0*
0&
b1010111000 >
b1110001010011 @
1<
b110 (
b110 ?
b101 A
1/
#610000
0$
0/
#615000
0<
1*
1&
1/
#620000
0/
#625000
1/
#630000
1!
b110100110110 "
b110100110110 3
b100011011011 #
b100011011011 5
0/
#635000
b110 0
b110100110110 )
b110100110110 4
b100011011011 '
b100011011011 6
b101 A
b10 B
1<
b111 (
b111 ?
0*
0&
1/
#640000
0!
0/
#645000
1*
1&
0<
1/
#650000
0/
#655000
1/
#660000
1!
b101111110010 "
b101111110010 3
b100110100101011 #
b100110100101011 5
0/
#665000
b101 A
b10 B
0*
0&
1<
b1000 (
b1000 ?
1/
#670000
0!
0/
#675000
0<
1*
1&
1/
#680000
0/
#685000
1/
#690000
1!
b110101111100 "
b110101111100 3
b1101100000111100 #
b1101100000111100 5
0/
#695000
b101 A
b10 B
1<
b1001 (
b1001 ?
0*
0&
1/
#700000
0!
0/
#705000
1*
1&
0<
1/
#710000
0/
#715000
1/
#720000
1!
b1100001100 "
b1100001100 3
b1101101001110 #
b1101101001110 5
0/
#725000
b101 A
b10 B
0*
0&
1<
b1010 (
b1010 ?
1/
#730000
0!
0/
#735000
0<
1*
1&
1/
#740000
0/
#745000
1/
#750000
1!
b10101110111 "
b10101110111 3
b1101100111111110 #
b1101100111111110 5
0/
#755000
b101 A
b10 B
1<
b1011 (
b1011 ?
0*
0&
1/
#760000
0!
0/
#765000
1*
1&
0<
1/
#770000
0/
#775000
1/
#780000
1$
0/
#785000
b1000 0
b1100001100 )
b1100001100 4
b1101101001110 '
b1101101001110 6
b10 B
0*
0&
b10101110111 >
b1101100111111110 @
1<
b1010 (
b1010 ?
b101 A
1/
#790000
0$
0/
#795000
0<
1*
1&
1/
#800000
0/
#805000
1/
#810000
1$
0/
#815000
b101 0
b1010111000 )
b1010111000 4
b1110001010011 '
b1110001010011 6
b10 B
1<
b1001 (
b1001 ?
0*
0&
b101 A
1/
#820000
0$
0/
#825000
1*
1&
0<
1/
#830000
0/
#835000
1/
#840000
1$
0/
#845000
b11 0
b11101110011 )
b11101110011 4
b10001110111100 '
b10001110111100 6
b10 B
0*
0&
1<
b1000 (
b1000 ?
b101 A
1/
#850000
0$
0/
#855000
0<
1*
1&
1/
#860000
0/
#865000
1/
#870000
1$
0/
#875000
b110101001010 )
b110101001010 4
b11111101000000 '
b11111101000000 6
b10 B
1<
b111 (
b111 ?
0*
0&
b101 A
1/
#880000
0$
0/
#885000
1*
1&
0<
1/
#890000
0/
#895000
1/
#900000
1$
0/
#905000
b101111110010 )
b101111110010 4
b100110100101011 '
b100110100101011 6
b10 B
0*
0&
1<
b110 (
b110 ?
b101 A
1/
#910000
0$
0/
#915000
0<
1*
1&
1/
#920000
0/
#925000
1/
#930000
1!
b10011101001 "
b10011101001 3
b110100100011100 #
b110100100011100 5
0/
#935000
b101 A
b10 B
1<
b111 (
b111 ?
0*
0&
1/
#940000
0!
0/
#945000
1*
1&
0<
1/
#950000
0/
#955000
1/
#960000
1$
0/
#965000
b10 0
b110011101 )
b110011101 4
b110000100011110 '
b110000100011110 6
b10 B
0*
0&
b10011101001 >
b110100100011100 @
1<
b110 (
b110 ?
b101 A
1/
#970000
0$
0/
#975000
0<
1*
1&
1/
#980000
0/
#985000
1/
#990000
1!
b1010100111 "
b1010100111 3
b1110011010001000 #
b1110011010001000 5
0/
#995000
b101 A
b10 B
1<
b111 (
b111 ?
0*
0&
1/
#1000000
0!
0/
#1005000
1*
1&
0<
1/
#1010000
0/
#1015000
1/
#1020000
1!
b1000000001 "
b1000000001 3
b1011111101100011 #
b1011111101100011 5
0/
#1025000
b101 A
b10 B
0*
0&
1<
b1000 (
b1000 ?
1/
#1030000
0!
0/
#1035000
0<
1*
1&
1/
#1040000
0/
#1045000
1/
#1050000
1!
b111001100010 "
b111001100010 3
b1001111001000101 #
b1001111001000101 5
0/
#1055000
b101 A
b10 B
1<
b1001 (
b1001 ?
0*
0&
1/
#1060000
0!
0/
#1065000
1*
1&
0<
1/
#1070000
0/
#1075000
1/
#1080000
1!
b111111111 "
b111111111 3
b1001000110100010 #
b1001000110100010 5
0/
#1085000
b101 A
b10 B
0*
0&
1<
b1010 (
b1010 ?
1/
#1090000
0!
0/
#1095000
0<
1*
1&
1/
#1100000
0/
#1105000
1/
#1110000
1$
0/
#1115000
b100 0
b10011101001 )
b10011101001 4
b110100100011100 '
b110100100011100 6
b10 B
b111111111 >
b1001000110100010 @
1<
b1001 (
b1001 ?
0*
0&
b101 A
1/
#1120000
0$
0/
#1125000
1*
1&
0<
1/
#1130000
0/
#1135000
1/
#1140000
1$
0/
#1145000
b111 0
b111111111 )
b111111111 4
b1001000110100010 '
b1001000110100010 6
b10 B
0*
0&
1<
b1000 (
b1000 ?
b101 A
1/
#1150000
0$
0/
#1155000
0<
1*
1&
1/
#1160000
0/
#1165000
1/
#1170000
1$
0/
#1175000
b110 0
b111001100010 )
b111001100010 4
b1001111001000101 '
b1001111001000101 6
b10 B
1<
b111 (
b111 ?
0*
0&
b101 A
1/
#1180000
0$
0/
#1185000
1*
1&
0<
1/
#1190000
0/
#1195000
1/
#1200000
1!
b101101110010 "
b101101110010 3
b1100110100000001 #
b1100110100000001 5
0/
#1205000
b101 A
b10 B
0*
0&
1<
b1000 (
b1000 ?
1/
#1210000
0!
0/
#1215000
0<
1*
1&
1/
#1220000
0/
#1225000
1/
#1230000
1!
b100001010110 "
b100001010110 3
b1101111011100 #
b1101111011100 5
0/
#1235000
b1000 0
b100001010110 )
b100001010110 4
b1101111011100 '
b1101111011100 6
b101 A
b10 B
1<
b1001 (
b1001 ?
0*
0&
1/
#1240000
0!
0/
#1245000
1*
1&
0<
1/
#1250000
0/
#1255000
1/
#1260000
1!
b1111010110 "
b1111010110 3
b1100101110100101 #
b1100101110100101 5
0/
#1265000
b101 A
b10 B
0*
0&
1<
b1010 (
b1010 ?
1/
#1270000
0!
0/
#1275000
0<
1*
1&
1/
#1280000
0/
#1285000
1/
#1290000
1!
b110111111010 "
b110111111010 3
b1111111111000 #
b1111111111000 5
0/
#1295000
b101 A
b10 B
1<
b1011 (
b1011 ?
0*
0&
1/
#1300000
0!
0/
#1305000
1*
1&
0<
1/
#1310000
0/
#1315000
1/
#1320000
1$
0/
#1325000
b1001 0
b110111111010 )
b110111111010 4
b1111111111000 '
b1111111111000 6
b10 B
0*
0&
b110111111010 >
b1111111111000 @
1<
b1010 (
b1010 ?
b101 A
1/
#1330000
0$
0/
#1335000
0<
1*
1&
1/
#1340000
0/
#1345000
1/
#1350000
1$
0/
#1355000
b110 0
b111001100010 )
b111001100010 4
b1001111001000101 '
b1001111001000101 6
b10 B
1<
b1001 (
b1001 ?
0*
0&
b101 A
1/
#1360000
0$
0/
#1365000
1*
1&
0<
1/
#1370000
0/
#1375000
1/
#1380000
1$
0/
#1385000
b101 0
b1000000001 )
b1000000001 4
b1011111101100011 '
b1011111101100011 6
b10 B
0*
0&
1<
b1000 (
b1000 ?
b101 A
1/
#1390000
0$
0/
#1395000
0<
1*
1&
1/
#1400000
0/
#1405000
1/
#1410000
1!
b101110001000 "
b101110001000 3
b1001100101110000 #
b1001100101110000 5
0/
#1415000
b1000 0
b101110001000 )
b101110001000 4
b1001100101110000 '
b1001100101110000 6
b101 A
b10 B
1<
b1001 (
b1001 ?
0*
0&
1/
#1420000
0!
0/
#1425000
1*
1&
0<
1/
#1430000
0/
#1435000
1/
#1440000
1$
0/
#1445000
b101 0
b1000000001 )
b1000000001 4
b1011111101100011 '
b1011111101100011 6
b10 B
0*
0&
b101110001000 >
b1001100101110000 @
1<
b1000 (
b1000 ?
b101 A
1/
#1450000
0$
0/
#1455000
0<
1*
1&
1/
#1460000
0/
#1465000
1/
#1470000
1$
0/
#1475000
b110 0
b1111010110 )
b1111010110 4
b1100101110100101 '
b1100101110100101 6
b10 B
1<
b111 (
b111 ?
0*
0&
b101 A
1/
#1480000
0$
0/
#1485000
1*
1&
0<
1/
#1490000
0/
#1495000
1/
#1500000
1!
b110010110000 "
b110010110000 3
b1000011011111011 #
b1000011011111011 5
0/
#1505000
b111 0
b110010110000 )
b110010110000 4
b1000011011111011 '
b1000011011111011 6
b101 A
b10 B
0*
0&
1<
b1000 (
b1000 ?
1/
#1510000
0!
0/
#1515000
0<
1*
1&
1/
#1520000
0/
#1525000
1/
#1530000
1$
0/
#1535000
b110 0
b1111010110 )
b1111010110 4
b1100101110100101 '
b1100101110100101 6
b10 B
b110010110000 >
b1000011011111011 @
1<
b111 (
b111 ?
0*
0&
b101 A
1/
#1540000
0$
0/
#1545000
1*
1&
0<
1/
#1550000
0/
#1555000
1/
#1560000
1$
0/
#1565000
b101 0
b101101110010 )
b101101110010 4
b1100110100000001 '
b1100110100000001 6
b10 B
0*
0&
1<
b110 (
b110 ?
b101 A
1/
#1570000
0$
0/
#1575000
0<
1*
1&
1/
#1580000
0/
#1585000
1/
#1590000
1!
b10110000100 "
b10110000100 3
b1011001111011 #
b1011001111011 5
0/
#1595000
b110 0
b10110000100 )
b10110000100 4
b1011001111011 '
b1011001111011 6
b101 A
b10 B
1<
b111 (
b111 ?
0*
0&
1/
#1600000
0!
0/
#1605000
1*
1&
0<
1/
#1610000
0/
#1615000
1/
#1620000
1!
b111000010110 "
b111000010110 3
b1010100001001110 #
b1010100001001110 5
0/
#1625000
b101 A
b10 B
0*
0&
1<
b1000 (
b1000 ?
1/
#1630000
0!
0/
#1635000
0<
1*
1&
1/
#1640000
0/
#1645000
1/
#1650000
1$
0/
#1655000
b111000010110 )
b111000010110 4
b1010100001001110 '
b1010100001001110 6
b10 B
b111000010110 >
b1010100001001110 @
1<
b111 (
b111 ?
0*
0&
b101 A
1/
#1660000
0$
0/
#1665000
1*
1&
0<
1/
#1670000
0/
#1675000
1/
#1680000
1!
b1011000011 "
b1011000011 3
b1001110101010010 #
b1001110101010010 5
0/
#1685000
b111 0
b1011000011 )
b1011000011 4
b1001110101010010 '
b1001110101010010 6
b101 A
b10 B
0*
0&
1<
b1000 (
b1000 ?
1/
#1690000
0!
0/
#1695000
0<
1*
1&
1/
#1700000
0/
#1705000
1/
#1710000
1!
b1001010100 "
b1001010100 3
b1100000111110001 #
b1100000111110001 5
0/
#1715000
b101 A
b10 B
1<
b1001 (
b1001 ?
0*
0&
1/
#1720000
0!
0/
#1725000
1*
1&
0<
1/
#1730000
0/
#1735000
1/
#1740000
1!
b110001000100 "
b110001000100 3
b1001010011100010 #
b1001010011100010 5
0/
#1745000
b1001 0
b110001000100 )
b110001000100 4
b1001010011100010 '
b1001010011100010 6
b101 A
b10 B
0*
0&
1<
b1010 (
b1010 ?
1/
#1750000
0!
0/
#1755000
0<
1*
1&
1/
#1760000
0/
#1765000
1/
#1770000
1!
b100110100 "
b100110100 3
b1111111101000100 #
b1111111101000100 5
0/
#1775000
b100110100 ,
b100110100 1
b1111111101000100 +
b1111111101000100 2
b101 A
b10 B
1<
b1011 (
b1011 ?
0*
0&
1/
#1780000
0!
0/
#1785000
1*
1&
0<
1/
#1790000
0/
#1795000
1/
#1800000
1$
0/
#1805000
b111 0
b1011000011 )
b1011000011 4
b1001110101010010 '
b1001110101010010 6
b10 B
0*
0&
b100110100 >
b1111111101000100 @
1<
b1010 (
b1010 ?
b101 A
1/
#1810000
0$
0/
#1815000
0<
1*
1&
1/
