src/pifo_test/rtl/pifo_reg.v
`timescale 1ns/1ps

module pifo_reg
#(
    parameter L2_REG_WIDTH = 4,
    parameter RANK_WIDTH = 16,
    parameter META_WIDTH = 12
)
(
    input                       rst,
    input                       clk,

    // Insertion interface
    output reg                  full,
    input                       insert,
    input [RANK_WIDTH-1:0]      rank_in,
    input [META_WIDTH-1:0]      meta_in,

    // Removal interface
    output reg                  valid_out,
    input                       remove,
    output [RANK_WIDTH-1:0]     rank_out,
    output [META_WIDTH-1:0]     meta_out,

    // Max entry (evicted upon inserting into full reg)
    output reg                  max_valid_out,
    output [RANK_WIDTH-1:0]     max_rank_out,
    output [META_WIDTH-1:0]     max_meta_out,

    // Stats
    output reg [L2_REG_WIDTH:0] num_entries,
    output reg                  empty
);

    localparam REG_WIDTH = 2**L2_REG_WIDTH;
    localparam COMP_LVLS = L2_REG_WIDTH+1;

    reg [RANK_WIDTH-1:0] rank[0:REG_WIDTH-1];
    reg [META_WIDTH-1:0] meta[0:REG_WIDTH-1];
    reg valid[0:REG_WIDTH-1];
    reg [RANK_WIDTH-1:0] min_rank[0:COMP_LVLS-1][0:REG_WIDTH-1];
    reg [META_WIDTH-1:0] min_meta[0:COMP_LVLS-1][0:REG_WIDTH-1];
    reg [L2_REG_WIDTH-1:0] min_idx[0:COMP_LVLS-1][0:REG_WIDTH-1];
    reg [RANK_WIDTH-1:0] max_rank[0:COMP_LVLS-1][0:REG_WIDTH-1];
    reg [META_WIDTH-1:0] max_meta[0:COMP_LVLS-1][0:REG_WIDTH-1];
    reg [L2_REG_WIDTH-1:0] max_idx[0:COMP_LVLS-1][0:REG_WIDTH-1];
    reg mvalid[0:COMP_LVLS-1][0:REG_WIDTH-1];
    wire [L2_REG_WIDTH-1:0] idx;
    reg insert_ltch;
    reg calc_min_max;
    integer i, j;
    reg [RANK_WIDTH-1:0] rank_in_ltch;
    reg [META_WIDTH-1:0] meta_in_ltch;
    
   always @(*)
    begin
        for (j = 0; j < REG_WIDTH; j=j+1)
        begin
            min_rank[0][j] <= rank[j];
            min_meta[0][j] <= meta[j];
            min_idx[0][j]  <= j;
            max_rank[0][j] <= rank[j];
            max_meta[0][j] <= meta[j];
            max_idx[0][j]  <= j;
            mvalid[0][j]   <= valid[j];
        end

        for (i = 0; i < COMP_LVLS; i=i+1)
            for (j = 0; j < REG_WIDTH/2**i; j=j+2) 
            begin
                if (((min_rank[i][j] <= min_rank[i][j+1]) && (mvalid[i][j] == 1'b1) && (mvalid[i][j+1] == 1'b1)) ||
                    ((mvalid[i][j] == 1'b1) && (mvalid[i][j+1] !== 1'b1)))
                begin
                    min_rank[i+1][j/2] <= min_rank[i][j];
                    min_meta[i+1][j/2] <= min_meta[i][j];
                    min_idx[i+1][j/2]  <= min_idx[i][j];
                end
                else begin
                    min_rank[i+1][j/2] <= min_rank[i][j+1];
                    min_meta[i+1][j/2] <= min_meta[i][j+1];
                    min_idx[i+1][j/2]  <= min_idx[i][j+1];                      
                end
                
                if (((max_rank[i][j] > max_rank[i][j+1]) && (mvalid[i][j] == 1'b1) && (mvalid[i][j+1] == 1'b1)) ||
                    ((mvalid[i][j] == 1'b1) && (mvalid[i][j+1] !== 1'b1)))
                begin
                    max_rank[i+1][j/2] <= max_rank[i][j];
                    max_meta[i+1][j/2] <= max_meta[i][j];
                    max_idx[i+1][j/2]  <= max_idx[i][j];
                end
                else begin
                    max_rank[i+1][j/2] <= max_rank[i][j+1];
                    max_meta[i+1][j/2] <= max_meta[i][j+1];
                    max_idx[i+1][j/2]  <= max_idx[i][j+1];                      
                end
                
                if ((mvalid[i][j] == 1'b1) || (mvalid[i][j+1] == 1'b1))
                    mvalid[i+1][j/2] <= 1'b1;
                else
                    mvalid[i+1][j/2] <= 1'b0;
            end
    end

    // Output min and max
    assign rank_out = min_rank[COMP_LVLS-1][0];
    assign meta_out = min_meta[COMP_LVLS-1][0];
    assign idx = min_idx[COMP_LVLS-1][0];
    assign max_rank_out = max_rank[COMP_LVLS-1][0];
    assign max_meta_out = max_meta[COMP_LVLS-1][0];
    
    // Min/max valid generation
    always @(posedge clk)
    begin
        if (rst)
        begin
            valid_out <= 1'b0;
            max_valid_out <= 1'b0;
        end
        else
        begin
            if (insert == 1'b1 || remove == 1'b1)
            begin
                valid_out <= 1'b0;
                max_valid_out <= 1'b0;
            end

            if (calc_min_max == 1'b1)
                if (num_entries > 0)
                begin
                    valid_out <= 1'b1;
                    max_valid_out <= 1'b1;
                end
        end
    end
        
    // Insert/Remove
    always @(posedge clk)
    begin
        if (rst)
        begin
            num_entries <= 0;
            calc_min_max <= 0;
            insert_ltch <= 0;
            empty <= 1'b0;
            full <= 1'b0;
        end
        else 
        begin
            calc_min_max <= 0;
            
            if (remove == 1'b1 && num_entries > 0)
            begin
                // Close gap 
                for (i = 0; i < REG_WIDTH; i=i+1)
                    if (i > idx)
                    begin
                        rank[i-1] <= rank[i];
                        meta[i-1] <= meta[i];
                        valid[i-1] <= valid[i];
                    end
                valid[num_entries-1] <= 0;
                if (num_entries == 1)
                    empty <= 1'b1;
                full <= (insert == 0) ? 1'b0 : full;
                num_entries <= num_entries - 1;
                calc_min_max <= 1;
                insert_ltch <= insert;
                rank_in_ltch <= rank_in;
                meta_in_ltch <= meta_in;
            end
            else if (insert == 1'b1 || insert_ltch == 1'b1)
            begin
                // Insert new value at end of register
                if (num_entries < REG_WIDTH)
                begin
                    rank[num_entries] <= (insert) ? rank_in : rank_in_ltch;
                    meta[num_entries] <= (insert) ? meta_in : meta_in_ltch;
                    valid[num_entries] <= 1;
                    if (num_entries == REG_WIDTH-1)
                        full <= 1'b1;
                    else
                        full <= 1'b0;
                    num_entries <= num_entries + 1;
                end
                else
                begin
                    // If new value is smaller than max
                    if (insert) begin
                        if (rank_in < max_rank[COMP_LVLS-1][0]) begin
                            // Replace largest value
                            rank[max_idx[COMP_LVLS-1][0]] <= rank_in;
                            meta[max_idx[COMP_LVLS-1][0]] <= meta_in;
                        end
                    end
                    else begin
                        if (rank_in_ltch < max_rank[COMP_LVLS-1][0]) begin
                            // Replace largest value
                            rank[max_idx[COMP_LVLS-1][0]] <= rank_in_ltch;
                            meta[max_idx[COMP_LVLS-1][0]] <= meta_in_ltch;
                        end
                    end
                    full <= 1'b1;
                end
                empty <= 1'b0;
                calc_min_max <= 1;
                insert_ltch <= 0;
            end
        end
    end
    
endmodule

src/pifo_test/wrappers/pifo_reg_wrapper.v
module pifo_reg_wrapper (
    output reg clk,
    input rst,

    input insert,
    input [15:0] rank_in,
    input [11:0] meta_in,

    input remove,

    output valid_out,
    output [15:0] rank_out,
    output [11:0] meta_out,
    output empty,
    output full,

    output max_valid_out,
    output [15:0] max_rank_out,
    output [11:0] max_meta_out,
    output [4:0] num_entries
);

pifo_reg dut (
    .clk(clk),
    .rst(rst),
    .insert(insert),
    .rank_in(rank_in),
    .meta_in(meta_in),
    .remove(remove),
    .valid_out(valid_out),
    .rank_out(rank_out),
    .meta_out(meta_out),
    .max_valid_out(max_valid_out),   
    .max_rank_out(max_rank_out),
    .max_meta_out(max_meta_out),
    .num_entries(num_entries),
    .empty(empty),
    .full(full)
);

initial begin
    $dumpfile("pifo_sim.vcd");
    $dumpvars(0, pifo_reg_wrapper);  
    clk = 0;
    forever #5 clk = ~clk;
end

endmodule

src/pifo_test/tests/pifo_sim.vcd
$date
	Wed Aug  6 14:24:18 2025
$end
$version
	Icarus Verilog
$end
$timescale
	1ps
$end
$scope module pifo_reg_wrapper $end
$var wire 1 ! insert $end
$var wire 12 " meta_in [11:0] $end
$var wire 16 # rank_in [15:0] $end
$var wire 1 $ remove $end
$var wire 1 % rst $end
$var wire 1 & valid_out $end
$var wire 16 ' rank_out [15:0] $end
$var wire 5 ( num_entries [4:0] $end
$var wire 12 ) meta_out [11:0] $end
$var wire 1 * max_valid_out $end
$var wire 16 + max_rank_out [15:0] $end
$var wire 12 , max_meta_out [11:0] $end
$var wire 1 - full $end
$var wire 1 . empty $end
$var reg 1 / clk $end
$scope module dut $end
$var wire 1 / clk $end
$var wire 4 0 idx [3:0] $end
$var wire 1 ! insert $end
$var wire 12 1 max_meta_out [11:0] $end
$var wire 16 2 max_rank_out [15:0] $end
$var wire 12 3 meta_in [11:0] $end
$var wire 12 4 meta_out [11:0] $end
$var wire 16 5 rank_in [15:0] $end
$var wire 16 6 rank_out [15:0] $end
$var wire 1 $ remove $end
$var wire 1 % rst $end
$var parameter 33 7 COMP_LVLS $end
$var parameter 32 8 L2_REG_WIDTH $end
$var parameter 32 9 META_WIDTH $end
$var parameter 32 : RANK_WIDTH $end
$var parameter 32 ; REG_WIDTH $end
$var reg 1 < calc_min_max $end
$var reg 1 . empty $end
$var reg 1 - full $end
$var reg 1 = insert_ltch $end
$var reg 1 * max_valid_out $end
$var reg 12 > meta_in_ltch [11:0] $end
$var reg 5 ? num_entries [4:0] $end
$var reg 16 @ rank_in_ltch [15:0] $end
$var reg 1 & valid_out $end
$var integer 32 A i [31:0] $end
$var integer 32 B j [31:0] $end
$upscope $end
$upscope $end
$enddefinitions $end
$comment Show the parameter values. $end
$dumpall
b10000 ;
b10000 :
b1100 9
b100 8
b101 7
$end
#0
$dumpvars
bx B
bx A
bx @
bx ?
bx >
x=
x<
bx 6
b0 5
bx 4
b0 3
bx 2
bx 1
bx 0
0/
x.
x-
bx ,
bx +
x*
bx )
bx (
bx '
x&
1%
0$
b0 #
b0 "
0!
$end
#5000
0*
0&
0-
0.
0=
0<
b0 (
b0 ?
1/
#10000
0%
0/
#15000
1/
#20000
0/
#25000
1/
#30000
1!
b1100011001 "
b1100011001 3
b11010101 #
b11010101 5
0/
#35000
b1100011001 ,
b1100011001 1
b11010101 +
b11010101 2
b0 0
b1100011001 )
b1100011001 4
b11010101 '
b11010101 6
b101 A
b10 B
1<
b1 (
b1 ?
1/
#40000
0!
0/
#45000
1*
1&
0<
1/
#50000
0/
#55000
1/
#60000
1!
b111010000 "
b111010000 3
b101 #
b101 5
0/
#65000
b1 0
b111010000 )
b111010000 4
b101 '
b101 6
b101 A
b10 B
0*
0&
1<
b10 (
b10 ?
1/
#70000
0!
0/
#75000
0<
1*
1&
1/
#80000
0/
#85000
1/
#90000
1!
b10100000101 "
b10100000101 3
b1111001 #
b1111001 5
0/
#95000
b101 A
b10 B
1<
b11 (
b11 ?
0*
0&
1/
#100000
0!
0/
#105000
1*
1&
0<
1/
#110000
0/
#115000
1/
#120000
1!
b111011010 "
b111011010 3
b10100110 #
b10100110 5
0/
#125000
b101 A
b10 B
0*
0&
1<
b100 (
b100 ?
1/
#130000
0!
0/
#135000
0<
1*
1&
1/
#140000
0/
#145000
1/
#150000
1!
b111000101011 "
b111000101011 3
b1110011 #
b1110011 5
0/
#155000
b101 A
b10 B
1<
b101 (
b101 ?
0*
0&
1/
#160000
0!
0/
#165000
1*
1&
0<
1/
#170000
0/
#175000
1/
#180000
1!
b1111011 "
b1111011 3
b1100100 #
b1100100 5
0/
#185000
b101 A
b10 B
0*
0&
1<
b110 (
b110 ?
1/
#190000
0!
0/
#195000
0<
1*
1&
1/
#200000
0/
#205000
1/
#210000
1!
b111001000 "
b111001000 3
0/
#215000
b101 A
b10 B
1<
b111 (
b111 ?
0*
0&
1/
#220000
0!
0/
#225000
1*
1&
0<
1/
#230000
0/
#235000
1/
#240000
0/
#245000
1/
#250000
1$
0/
#255000
b100 0
b1111011 )
b1111011 4
b1100100 '
b1100100 6
b10 B
b111001000 >
b1100100 @
1<
b110 (
b110 ?
0*
0&
b101 A
1/
#260000
0$
0/
#265000
1*
1&
0<
1/
#270000
0/
#275000
1/
#280000
0/
#285000
1/
#290000
1$
0/
#295000
b111001000 )
b111001000 4
b10 B
1<
b101 (
b101 ?
0*
0&
b101 A
1/
#300000
0$
0/
#305000
1*
1&
0<
1/
#310000
0/
#315000
1/
#320000
0/
#325000
1/
#330000
1$
0/
#335000
b11 0
b111000101011 )
b111000101011 4
b1110011 '
b1110011 6
b10 B
1<
b100 (
b100 ?
0*
0&
b101 A
1/
#340000
0$
0/
#345000
1*
1&
0<
1/
#350000
0/
#355000
1/
#360000
0/
#365000
1/
#370000
1$
0/
#375000
b1 0
b10100000101 )
b10100000101 4
b1111001 '
b1111001 6
b10 B
1<
b11 (
b11 ?
0*
0&
b101 A
1/
#380000
0$
0/
#385000
1*
1&
0<
1/
#390000
0/
#395000
1/
#400000
0/
#405000
1/
#410000
1$
0/
#415000
b111011010 )
b111011010 4
b10100110 '
b10100110 6
b10 B
1<
b10 (
b10 ?
0*
0&
b101 A
1/
#420000
0$
0/
#425000
1*
1&
0<
1/
#430000
0/
#435000
1/
#440000
0/
#445000
1/
#450000
1$
0/
#455000
b0 0
b1100011001 )
b1100011001 4
b11010101 '
b11010101 6
b10 B
1<
b1 (
b1 ?
0*
0&
b101 A
1/
#460000
0$
0/
#465000
1*
1&
0<
1/
#470000
0/
#475000
1/
#480000
0/
#485000
1/
#490000
1$
0/
#495000
bx ,
bx 1
bx +
bx 2
b1111 0
bx )
bx 4
bx '
bx 6
b10 B
1<
b0 (
b0 ?
1.
0*
0&
b101 A
1/
#500000
0$
0/
#505000
0<
1/
